<?xml version="1.0" encoding="UTF-8"?>
<!-- Copyright (C) 2015 The Android Open Source Project

     Licensed under the Apache License, Version 2.0 (the "License");
     you may not use this file except in compliance with the License.
     You may obtain a copy of the License at

          http://www.apache.org/licenses/LICENSE-2.0

     Unless required by applicable law or agreed to in writing, software
     distributed under the License is distributed on an "AS IS" BASIS,
     WITHOUT WARRANTIES OR CONDITIONS OF ANY KIND, either express or implied.
     See the License for the specific language governing permissions and
     limitations under the License.
-->
<!-- Copyright (C) 2018 NVIDIA Corporation.  All rights reserved. -->

<!-- List of all devicePorts supported in primary HAL -->
<devicePorts>
    <!-- Output devices declaration, i.e. Sink DEVICE PORT -->
    <devicePort tagName="Earpiece" type="AUDIO_DEVICE_OUT_EARPIECE" role="sink">
       <profile name="" format="AUDIO_FORMAT_PCM_16_BIT"
                samplingRates="48000" channelMasks="AUDIO_CHANNEL_OUT_STEREO"/>
    </devicePort>
    <devicePort tagName="Speaker" type="AUDIO_DEVICE_OUT_SPEAKER" role="sink">
        <profile name="" format="AUDIO_FORMAT_PCM_16_BIT"
                 samplingRates="48000" channelMasks="AUDIO_CHANNEL_OUT_STEREO"/>
    </devicePort>
    <devicePort tagName="Wired Headset" type="AUDIO_DEVICE_OUT_WIRED_HEADSET" role="sink">
        <profile name="" format="AUDIO_FORMAT_PCM_16_BIT"
                 samplingRates="48000" channelMasks="AUDIO_CHANNEL_OUT_STEREO"/>
    </devicePort>
    <devicePort tagName="Wired Headphones" type="AUDIO_DEVICE_OUT_WIRED_HEADPHONE" role="sink">
        <profile name="" format="AUDIO_FORMAT_PCM_16_BIT"
                 samplingRates="48000" channelMasks="AUDIO_CHANNEL_OUT_STEREO"/>
    </devicePort>
    <devicePort tagName="BT SCO" type="AUDIO_DEVICE_OUT_BLUETOOTH_SCO" role="sink">
        <profile name="" format="AUDIO_FORMAT_PCM_16_BIT"
                 samplingRates="8000,16000" channelMasks="AUDIO_CHANNEL_OUT_MONO"/>
    </devicePort>
    <devicePort tagName="BT SCO Headset" type="AUDIO_DEVICE_OUT_BLUETOOTH_SCO_HEADSET" role="sink">
        <profile name="" format="AUDIO_FORMAT_PCM_16_BIT"
                 samplingRates="8000,16000" channelMasks="AUDIO_CHANNEL_OUT_MONO"/>
    </devicePort>
    <devicePort tagName="BT SCO Car Kit" type="AUDIO_DEVICE_OUT_BLUETOOTH_SCO_CARKIT" role="sink">
        <profile name="" format="AUDIO_FORMAT_PCM_16_BIT"
                 samplingRates="8000,16000" channelMasks="AUDIO_CHANNEL_OUT_MONO"/>
    </devicePort>
    <devicePort tagName="AUX Digital" type="AUDIO_DEVICE_OUT_AUX_DIGITAL" role="sink">
        <profile name="" format="AUDIO_FORMAT_PCM_16_BIT"
                 samplingRates="48000" channelMasks="AUDIO_CHANNEL_OUT_STEREO"/>
    </devicePort>
    <devicePort tagName="Digital Dock HS" type="AUDIO_DEVICE_OUT_DGTL_DOCK_HEADSET" role="sink">
        <profile name="" format="AUDIO_FORMAT_PCM_16_BIT"
                 samplingRates="48000" channelMasks="AUDIO_CHANNEL_OUT_STEREO"/>
    </devicePort>
    <devicePort tagName="Gamecast-Out" type="AUDIO_DEVICE_OUT_GAMECAST" role="sink">
        <profile name="" format="AUDIO_FORMAT_PCM_16_BIT"
                 samplingRates="48000" channelMasks="AUDIO_CHANNEL_OUT_STEREO"/>
    </devicePort>

    <!-- Input devices declaration, i.e. Source DEVICE PORT -->
    <devicePort tagName="Built-In Mic" type="AUDIO_DEVICE_IN_BUILTIN_MIC" role="source">
        <profile name="" format="AUDIO_FORMAT_PCM_16_BIT"
                 samplingRates="8000,11025,12000,16000,22050,24000,32000,44100,48000"
                 channelMasks="AUDIO_CHANNEL_IN_MONO,AUDIO_CHANNEL_IN_STEREO"/>
    </devicePort>
    <devicePort tagName="Wired Headset Mic" type="AUDIO_DEVICE_IN_WIRED_HEADSET" role="source">
        <profile name="" format="AUDIO_FORMAT_PCM_16_BIT"
                 samplingRates="8000,11025,12000,16000,22050,24000,32000,44100,48000"
                 channelMasks="AUDIO_CHANNEL_IN_MONO,AUDIO_CHANNEL_IN_STEREO"/>
    </devicePort>
    <devicePort tagName="BT SCO Headset Mic" type="AUDIO_DEVICE_IN_BLUETOOTH_SCO_HEADSET" role="source">
        <profile name="" format="AUDIO_FORMAT_PCM_16_BIT"
                 samplingRates="8000,16000" channelMasks="AUDIO_CHANNEL_IN_MONO"/>
    </devicePort>
    <devicePort tagName="Digital Dock HS Mic" type="AUDIO_DEVICE_IN_DGTL_DOCK_HEADSET" role="source">
        <profile name="" format="AUDIO_FORMAT_PCM_16_BIT"
                 samplingRates="8000,11025,12000,16000,22050,24000,32000,44100,48000"
                 channelMasks="AUDIO_CHANNEL_IN_MONO,AUDIO_CHANNEL_IN_STEREO"/>
    </devicePort>
    <devicePort tagName="Gamecast-In" type="AUDIO_DEVICE_IN_GAMECAST" role="source">
        <profile name="" format="AUDIO_FORMAT_PCM_16_BIT"
                 samplingRates="8000,11025,12000,16000,22050,24000,32000,44100,48000"
                 channelMasks="AUDIO_CHANNEL_IN_MONO,AUDIO_CHANNEL_IN_STEREO"/>
    </devicePort>
    <devicePort tagName="AudioIP-In" type="AUDIO_DEVICE_IN_IP" role="source">
        <profile name="" format="AUDIO_FORMAT_PCM_16_BIT"
                 samplingRates="16000"
                 channelMasks="AUDIO_CHANNEL_IN_MONO,AUDIO_CHANNEL_IN_STEREO"/>
    </devicePort>
</devicePorts>
